<?xml version="1.0" encoding="utf-8"?>
<!DOCTYPE documentInfo>
<documentInfo url="/home/zach/Dropbox/Research/HUSL/Autorotation/Thesis/tamuthesis.pdf">
 <pageList/>
 <generalInfo>
  <history>
   <oldPage viewport="14;C2:0.499335:0.0195272:1"/>
   <oldPage viewport="13;C2:0.499335:0.045221:1"/>
   <oldPage viewport="12;C2:0.499335:0.00924974:1"/>
   <oldPage viewport="11;C2:0.499335:0.0349435:1"/>
   <oldPage viewport="10;C2:0.499335:-0.00102775:1"/>
   <oldPage viewport="9;C2:0.499335:0.024666:1"/>
   <oldPage viewport="8;C2:0.499335:0.975334:1"/>
   <oldPage viewport="9;C2:0.499335:0.024666:1"/>
   <oldPage viewport="8;C2:0.499335:0.913669:1"/>
   <oldPage viewport="9;C2:0.499335:0.456321:1"/>
   <current viewport="15;C2:0.165033:0.113636:2"/>
  </history>
  <views>
   <view name="PageView">
    <zoom mode="1" value="1.22876"/>
   </view>
  </views>
 </generalInfo>
</documentInfo>
